{"39454232": {"date": "2024 Oct 24", "title": "Global, regional, and national burden of injuries, and burden attributable to injuries risk factors, 1990 to 2019: results from the Global Burden of Disease study 2019", "abstract": "Objectives:\n        \n      \n      In this study, the trends and current situation of the injury burden as well as attributable burden to injury risk factors at global, regional, and national levels based on the Global Burden of Diseases, Injuries, and Risk Factors Study (GBD) 2019 are presented.", "author_names": "GBD 2019 Injuries Collaborators", "author_ids": "/?term=GBD+2019+Injuries+Collaborators%5BCorporate+Author%5D", "doi": "10.1016/j.puhe.2024.06.011", "pmid": "39454232"}}